atzlib/__init__.py
atzlib/ezpsql.py
atzlib/main.py
atzlib/utils/auth.py
atzlib/utils/chatbox.py
atzlib/utils/dataloader.py
atzlib/utils/translate.py
atzlib-0.1.3.dist-info/METADATA
atzlib-0.1.3.dist-info/WHEEL
atzlib-0.1.3.dist-info/RECORD
