Metadata-Version: 2.1
Name: atzlib
Version: 0.1.3
Summary: My python codes.
License: MIT
Author: jhlee29
Author-email: leejinha829@gmail.com
Requires-Python: >=3.9,<4.0
Classifier: License :: OSI Approved :: MIT License
Classifier: Programming Language :: Python :: 3
Classifier: Programming Language :: Python :: 3.9
Classifier: Programming Language :: Python :: 3.10
Classifier: Programming Language :: Python :: 3.11
Classifier: Programming Language :: Python :: 3.12
Requires-Dist: pandas (>=2.2.3,<3.0.0)
Requires-Dist: psycopg2 (>=2.9.10,<3.0.0)
Requires-Dist: python-dotenv (>=1.0.1,<2.0.0)
Requires-Dist: sqlalchemy (>=1.4,<2.0.36)
